[
  {
    "name": "attachments-counter",
    "selector": "dso-attachments-counter.hydrated",
    "stories": ["attachments-counter"],
    "type": "core"
  },
  {
    "name": "badge",
    "selector": "dso-badge.hydrated",
    "stories": ["attention", "error", "info", "outline", "plain", "primary", "success", "warning"],
    "type": "core"
  },
  {
    "name": "banner",
    "selector": "dso-banner.hydrated",
    "stories": ["success", "error", "info", "warning", "rich-warning"],
    "type": "core"
  },
  {
    "name": "card-container",
    "selector": "dso-card-container.hydrated",
    "stories": ["card-list", "card-grid"],
    "type": "core"
  },
  {
    "name": "highlight-box",
    "selector": "dso-highlight-box.hydrated",
    "stories": ["default", "yellow", "white-with-dropshadow", "with-border", "with-icon", "with-banner-image"],
    "type": "core"
  },
  { "name": "icon", "selector": "dso-icon.hydrated", "stories": ["default"], "type": "core" },
  {
    "name": "icon",
    "selector": "#icon-overview-list",
    "stories": ["overview"],
    "type": "core"
  },
  {
    "name": "info-button",
    "selector": "dso-info-button.hydrated",
    "stories": ["inactive", "active", "secondary-inactive", "secondary-active"],
    "type": "core"
  },
  {
    "name": "info",
    "selector": "dso-info.hydrated",
    "stories": ["default", "fixed"],
    "type": "core"
  },
  {
    "name": "list-button",
    "selector": "dso-list-button.hydrated",
    "stories": ["single-select", "multi-select"],
    "type": "core"
  },
  {
    "name": "progress-bar-deprecated",
    "selector": "dso-progress-bar.hydrated",
    "stories": ["default", "arbitrary-values"],
    "type": "core"
  },
  {
    "name": "link",
    "selector": "#dt-i18n-decorator-container a",
    "stories": [
      "default",
      "download-link",
      "external-link",
      "link-with-icon",
      "mail-link-with-icon",
      "phone-link-with-icon"
    ],
    "type": "html-css"
  },
  {
    "name": "application-heading",
    "selector": ".dso-app-heading",
    "stories": ["default", "with-subtitle", "with-subtitle-and-steps", "subtitle-only", "subtitle-and-steps-only"],
    "type": "html-css"
  },
  {
    "name": "attachments-counter",
    "selector": ".dso-attachments",
    "stories": ["attachments-counter"],
    "type": "html-css"
  },
  {
    "name": "badge-deprecated",
    "selector": ".dso-badge",
    "stories": ["attention", "error", "info", "outline", "plain", "primary", "success", "warning"],
    "type": "html-css"
  },
  {
    "name": "banner",
    "selector": ".dso-banner",
    "stories": [
      "success",
      "error",
      "info",
      "info-compact-non-removable",
      "info-non-removable",
      "rich-info",
      "rich-warning",
      "warning"
    ],
    "type": "html-css"
  },
  { "name": "breadcrumbs", "selector": "ol.dso-breadcrumbs", "stories": ["breadcrumbs"], "type": "html-css" },
  {
    "name": "button",
    "selector": ".dso-primary",
    "stories": ["primary", "primary-compact"],
    "type": "html-css"
  },
  {
    "name": "button",
    "selector": ".dso-secondary",
    "stories": ["secondary"],
    "type": "html-css"
  },
  {
    "name": "button",
    "selector": ".dso-tertiary",
    "stories": ["tertiary"],
    "type": "html-css"
  },
  {
    "name": "button-row",
    "selector": ".dso-button-row",
    "stories": [
      "alle-button-varianten",
      "default",
      "emphasized",
      "primaire-button-varianten",
      "secundaire-button-varianten",
      "tertiaire-button-varianten"
    ],
    "type": "html-css"
  },
  { "name": "card-grid", "selector": ".dso-card-grid", "stories": ["card-grid"], "type": "html-css" },
  { "name": "card-list", "selector": ".dso-card-list", "stories": ["card-list"], "type": "html-css" },
  {
    "name": "context",

    "stories": ["label", "label-align-left", "legend", "legend-align-left"],
    "type": "html-css"
  },
  {
    "name": "definition-list",
    "selector": "dl",
    "stories": [
      "bordered",
      "column-variant-one-three",
      "column-variant-three-one",
      "column-variant-two-two",
      "columns-list",
      "default",
      "emphasize-description",
      "three-columns",
      "three-columns-small",
      "two-columns",
      "two-columns-small",
      "vertical",
      "vertical-with-emphasize-description"
    ],
    "type": "html-css"
  },
  {
    "name": "description",
    "selector": ".dso-description-term",
    "stories": ["example", "term"],
    "type": "html-css"
  },
  {
    "name": "document-header",
    "selector": ".dso-document-header",
    "stories": [
      "default",
      "default-besluitversie",
      "default-ontwerp",
      "sticky",
      "sticky-besluitversie",
      "sticky-ontwerp"
    ],
    "type": "html-css"
  },
  {
    "name": "footer",
    "type": "html-css",
    "stories": ["footer"],
    "selector": "footer"
  },
  { "name": "footnotes", "stories": ["example"], "type": "html-css" },
  { "name": "footnotes", "selector": ".dso-footnotes", "stories": ["list"], "type": "html-css" },
  {
    "name": "footnotes",
    "selector": ".dso-footnote-reference",
    "stories": ["reference"],
    "type": "html-css"
  },
  {
    "name": "form",

    "stories": ["horizontal", "horizontal-collections", "vertical", "vertical-collections", "single-page"],
    "type": "html-css"
  },
  {
    "name": "form-buttons",
    "stories": ["default", "multi-page", "sections", "simple-form"],
    "type": "html-css"
  },
  {
    "name": "form-group",

    "stories": [
      "checkboxes",
      "confirm",
      "date-picker",
      "files",
      "no-files",
      "input",
      "radios",
      "search-bar",
      "select",
      "static",
      "textarea"
    ],
    "type": "html-css"
  },
  {
    "name": "justify-form-groups",

    "stories": ["justify-form-groups"],
    "type": "html-css"
  },
  {
    "name": "highlight-box",
    "selector": ".dso-highlight-box",
    "stories": [
      "default",
      "grey",
      "grey-with-border",
      "white-with-dropshadow",
      "with-banner-image",
      "with-border",
      "with-icon",
      "yellow"
    ],
    "type": "html-css"
  },
  {
    "name": "image",
    "selector": "img",
    "stories": ["default", "responsive", "circle"],
    "type": "html-css"
  },
  {
    "name": "info",
    "selector": ".dso-info:not(.dso-accordion-section)",
    "stories": ["default", "fixed"],
    "type": "html-css"
  },
  {
    "name": "info-button",
    "selector": ".dso-info-button",
    "stories": ["inactive", "active", "secondary-inactive", "secondary-active"],
    "type": "html-css"
  },
  { "name": "label-group", "selector": ".dso-label-group", "stories": ["label-group"], "type": "html-css" },
  {
    "name": "link-list",
    "selector": ".dso-link-list",
    "stories": ["ul", "ol", "in-nav", "in-footer"],
    "type": "html-css"
  },
  {
    "name": "link-list",

    "stories": ["in-highlight-box"],
    "type": "html-css"
  },
  {
    "name": "list",

    "stories": ["unordered", "ordered", "group", "columns", "image-list", "unstyled", "icons", "ordered-action"],
    "type": "html-css"
  },
  {
    "name": "navbar",
    "selector": ".dso-navbar",
    "stories": ["primary", "secondary"],
    "type": "html-css"
  },
  {
    "name": "navbar",

    "stories": ["with-extension"],
    "type": "html-css"
  },
  {
    "name": "paragraph",

    "stories": ["default", "disclaimer"],
    "type": "html-css"
  },
  {
    "name": "progress-bar-deprecated",
    "selector": ".progress",
    "stories": ["default", "arbitrary-values"],
    "type": "html-css"
  },
  {
    "name": "rich-content",

    "stories": ["rich-content"],
    "type": "html-css"
  },
  {
    "name": "row-equal-heights",
    "selector": ".row.dso-equal-heights",
    "stories": ["highlight-boxes", "tiles"],
    "type": "html-css"
  },
  {
    "name": "search-bar",
    "selector": ".dso-search-bar",
    "stories": [
      "visual-label-with-icon",
      "visual-label-without-icon",
      "placeholder-with-long-text",
      "hidden-label-with-icon",
      "hidden-label-without-icon",
      "with-value",
      "invalid",
      "hidden-button",
      "with-results-message",
      "with-hidden-results-message"
    ],
    "type": "html-css"
  },
  {
    "name": "shopping-cart",
    "selector": ".dso-shopping-cart ",
    "stories": [
      "default",
      "items-collapsed",
      "items-non-collapsable",
      "remove-all-items-option",
      "edit-items",
      "with-subitems",
      "with-subitems-and-hidden-summary",
      "with-subitems-and-warning"
    ],
    "type": "html-css"
  },
  {
    "name": "table",
    "selector": "dso-table.hydrated",
    "type": "core",
    "stories": [
      "data-grid",
      "data-table",
      "sorted-ascending",
      "sorted-descending",
      "with-dso-image-overlay",
      "with-vertical-lines"
    ]
  },
  {
    "name": "tile",
    "selector": ".dso-tile",
    "stories": ["default", "theme"],
    "type": "html-css"
  },
  {
    "name": "tile-grid",
    "selector": ".dso-tile-grid",
    "stories": ["tile-grid"],
    "type": "html-css"
  },
  {
    "name": "viewer-grid",
    "selector": "dso-viewer-grid",
    "stories": ["document-panel", "filter-panel", "viewer-grid"],
    "type": "core"
  }
]
